{
    "libcamera": {
        "cargoLocks": null,
        "date": "2024-11-11",
        "extract": null,
        "name": "libcamera",
        "passthru": null,
        "pinned": false,
        "src": {
            "deepClone": false,
            "fetchSubmodules": false,
            "leaveDotGit": false,
            "name": null,
            "owner": "raspberrypi",
            "repo": "libcamera",
            "rev": "75fe515ae832f9460ff867f449d05ff8ca995af7",
            "sha256": "sha256-HDLSRylRn/siR2HMTHLkH20QLjzH1R2iKWPca7eSWiU=",
            "type": "github"
        },
        "version": "75fe515ae832f9460ff867f449d05ff8ca995af7"
    },
    "libcamera-apps": {
        "cargoLocks": null,
        "date": "2024-11-12",
        "extract": null,
        "name": "libcamera-apps",
        "passthru": null,
        "pinned": false,
        "src": {
            "deepClone": false,
            "fetchSubmodules": false,
            "leaveDotGit": false,
            "name": null,
            "owner": "raspberrypi",
            "repo": "libcamera-apps",
            "rev": "50958df98d3cf77b54706a794226d556d649981c",
            "sha256": "sha256-dDb4/SL5SPuBhmp1g8h8ZMq9PnG2SZMIik2gnO8PkuY=",
            "type": "github"
        },
        "version": "50958df98d3cf77b54706a794226d556d649981c"
    },
    "mediamtx": {
        "cargoLocks": null,
        "date": "2024-11-08",
        "extract": null,
        "name": "mediamtx",
        "passthru": null,
        "pinned": false,
        "src": {
            "deepClone": false,
            "fetchSubmodules": false,
            "leaveDotGit": false,
            "name": null,
            "owner": "bluenviron",
            "repo": "mediamtx",
            "rev": "b7763454a98fb9e6b1b9ea3d3035f112d1d9fa85",
            "sha256": "sha256-lOeKUqCP3NC3qw7MTl9Bd9yuVSXXO3JM27FeXynha40=",
            "type": "github"
        },
        "version": "b7763454a98fb9e6b1b9ea3d3035f112d1d9fa85"
    }
}